b2sim/__init__.py
b2sim/analysis/__init__.py
b2sim/analysis/ai.py
b2sim/analysis/fitness.py
b2sim/analysis/graphing.py
b2sim/analysis/visualize.py
b2sim/engine/__init__.py
b2sim/engine/actions.py
b2sim/engine/alt_eco.py
b2sim/engine/farms.py
b2sim/engine/info.py
b2sim/engine/logger.py
b2sim/engine/main.py
b2sim/engine/rounds.py
b2sim/templates/eco_send_info.csv
b2sim/templates/nat_send_lengths.csv
b2sim-2.3.8.dist-info/licenses/LICENSE
b2sim-2.3.8.dist-info/METADATA
b2sim-2.3.8.dist-info/WHEEL
b2sim-2.3.8.dist-info/top_level.txt
b2sim-2.3.8.dist-info/RECORD
