Metadata-Version: 2.4
Name: b2sim
Version: 2.3.8
Summary: A library for the simulation of eco & farm based strategies in Bloons TD Battles 2
Author-email: redlaserbm <redlaserbm@gmail.com>
License:                     GNU GENERAL PUBLIC LICENSE
Project-URL: Homepage, https://github.com/redlaserbm/BTDB2_SIMULATOR/
Requires-Python: >=3.10
License-File: LICENSE
Provides-Extra: analysis
Requires-Dist: pandas; extra == "analysis"
Requires-Dist: matplotlib; extra == "analysis"
Dynamic: license-file
